{
  "date": "2026-04-11",
  "category": "artwork",
  "article_count": 3,
  "source_count": 1,
  "matched_count": 3,
  "top_entities": [
    {
      "name": "Artist",
      "count": 6
    },
    {
      "name": "ArtworkType",
      "count": 5
    },
    {
      "name": "CollectionChange",
      "count": 3
    },
    {
      "name": "Period",
      "count": 3
    },
    {
      "name": "Medium",
      "count": 2
    }
  ],
  "sources": {
    "Artsy Editorial": 3
  },
  "generated_at": "2026-04-11T19:45:11.314913+09:00"
}